aws_service_screener/CreateService.py
aws_service_screener/DocLinkValidity.py
aws_service_screener/RuleCount.py
aws_service_screener/Screener.py
aws_service_screener/__fork/tail.txt
aws_service_screener/adminlte/aws/res/.gitignore
aws_service_screener/adminlte/aws/res/LICENCE.md
aws_service_screener/adminlte/aws/res/dist/css/adminlte.min.css
aws_service_screener/adminlte/aws/res/dist/img/AdminLTELogo.png
aws_service_screener/adminlte/aws/res/dist/img/aws.png
aws_service_screener/adminlte/aws/res/dist/img/boxed-bg.jpg
aws_service_screener/adminlte/aws/res/dist/img/boxed-bg.png
aws_service_screener/adminlte/aws/res/dist/img/default-150x150.png
aws_service_screener/adminlte/aws/res/dist/img/icons.png
aws_service_screener/adminlte/aws/res/dist/js/.eslintrc.json
aws_service_screener/adminlte/aws/res/dist/js/adminlte.js
aws_service_screener/adminlte/aws/res/dist/js/adminlte.js.map
aws_service_screener/adminlte/aws/res/dist/js/adminlte.min.js
aws_service_screener/adminlte/aws/res/dist/js/adminlte.min.js.map
aws_service_screener/adminlte/aws/res/dist/js/demo.js
aws_service_screener/adminlte/aws/res/plugins/bootstrap/js/bootstrap.bundle.min.js
aws_service_screener/adminlte/aws/res/plugins/chart.js/Chart.min.js
aws_service_screener/adminlte/aws/res/plugins/datatables/jquery.dataTables.js
aws_service_screener/adminlte/aws/res/plugins/datatables/jquery.dataTables.min.js
aws_service_screener/adminlte/aws/res/plugins/datatables-bs4/css/dataTables.bootstrap4.css
aws_service_screener/adminlte/aws/res/plugins/datatables-bs4/css/dataTables.bootstrap4.min.css
aws_service_screener/adminlte/aws/res/plugins/datatables-bs4/js/dataTables.bootstrap4.js
aws_service_screener/adminlte/aws/res/plugins/datatables-bs4/js/dataTables.bootstrap4.min.js
aws_service_screener/adminlte/aws/res/plugins/datatables-buttons/css/buttons.bootstrap4.css
aws_service_screener/adminlte/aws/res/plugins/datatables-buttons/css/buttons.bootstrap4.min.css
aws_service_screener-2.0.0.dist-info/LICENSE
aws_service_screener-2.0.0.dist-info/METADATA
aws_service_screener-2.0.0.dist-info/WHEEL
aws_service_screener-2.0.0.dist-info/RECORD
