Metadata-Version: 2.1
Name: aws-service-screener
Version: 2.0.0
Summary: An open source guidance tool for AWS environments
License: Apache 2.0 license
Author: AWS
Author-email: aws-gh-ss@amazon.com
Requires-Python: >=3.8,<4.0
Classifier: License :: Other/Proprietary License
Classifier: Programming Language :: Python :: 3
Classifier: Programming Language :: Python :: 3.8
Classifier: Programming Language :: Python :: 3.9
Classifier: Programming Language :: Python :: 3.10
Classifier: Programming Language :: Python :: 3.11
Classifier: Programming Language :: Python :: 3.12
Requires-Dist: XlsxWriter (>=3.2.0,<4.0.0)
Requires-Dist: boto3 (>=1.34.76,<2.0.0)
Requires-Dist: netaddr (>=1.2.1,<2.0.0)
Requires-Dist: packaging (>=24.0,<25.0)
Requires-Dist: requests (>=2.31.0,<3.0.0)
